fabric_remote/__init__.py
fabric_remote/auth.py
fabric_remote/cors.py
fabric_remote/executions.py
fabric_remote/main.py
fabric_remote/stream.py
fabric_remote/tasks.py
fabric_remote/util.py
fabric_remote/views.py
fabric_remote-0.0.1.dist-info/DESCRIPTION.rst
fabric_remote-0.0.1.dist-info/entry_points.txt
fabric_remote-0.0.1.dist-info/METADATA
fabric_remote-0.0.1.dist-info/metadata.json
fabric_remote-0.0.1.dist-info/RECORD
fabric_remote-0.0.1.dist-info/top_level.txt
fabric_remote-0.0.1.dist-info/WHEEL
fixtures/__init__.py
fixtures/fabfile.py
