Metadata-Version: 2.0
Name: fabric-remote
Version: 0.0.1
Summary: UNKNOWN
Home-page: UNKNOWN
Author: UNKNOWN
Author-email: UNKNOWN
License: UNKNOWN
Platform: UNKNOWN
Requires-Dist: Flask (==0.10.1)
Requires-Dist: Fabric (==1.8.1)
Requires-Dist: shortuuid (==0.4)
Requires-Dist: Flask-Cors (==1.2.1)
